swh/scrubber/__init__.py
swh/scrubber/base_checker.py
swh/scrubber/cli.py
swh/scrubber/db.py
swh/scrubber/fixer.py
swh/scrubber/journal_checker.py
swh/scrubber/objstorage_checker.py
swh/scrubber/origin_locator.py
swh/scrubber/py.typed
swh/scrubber/storage_checker.py
swh/scrubber/utils.py
swh/scrubber/sql/20-enums.sql
swh/scrubber/sql/30-schema.sql
swh/scrubber/sql/60-indexes.sql
swh/scrubber/sql/upgrades/2.sql
swh/scrubber/sql/upgrades/3.sql
swh/scrubber/sql/upgrades/4.sql
swh/scrubber/sql/upgrades/5.sql
swh/scrubber/sql/upgrades/6.sql
swh/scrubber/sql/upgrades/7.sql
swh/scrubber/tests/__init__.py
swh/scrubber/tests/conftest.py
swh/scrubber/tests/objstorage_checker_tests.py
swh/scrubber/tests/storage_checker_tests.py
swh/scrubber/tests/test_cli.py
swh/scrubber/tests/test_db.py
swh/scrubber/tests/test_fixer.py
swh/scrubber/tests/test_init.py
swh/scrubber/tests/test_journal_kafka.py
swh/scrubber/tests/test_migration.py
swh/scrubber/tests/test_objstorage_memory.py
swh/scrubber/tests/test_objstorage_pathslicing.py
swh/scrubber/tests/test_origin_locator.py
swh/scrubber/tests/test_storage_cassandra.py
swh/scrubber/tests/test_storage_postgresql.py
swh/scrubber/tests/data/test/__init__.py
swh/scrubber/tests/data/test/postgresql/__init__.py
swh/scrubber/tests/data/test/postgresql/sql/10-init-all.sql
swh/scrubber/tests/data/test/postgresql/sql/20-data.sql
swh/scrubber/tests/data/test/postgresql/sql/upgrades/006.sql
swh/scrubber/tests/data/test/postgresql/sql/upgrades/007.sql
swh_scrubber-4.0.0.dist-info/licenses/AUTHORS
swh_scrubber-4.0.0.dist-info/licenses/LICENSE
swh_scrubber-4.0.0.dist-info/METADATA
swh_scrubber-4.0.0.dist-info/WHEEL
swh_scrubber-4.0.0.dist-info/entry_points.txt
swh_scrubber-4.0.0.dist-info/top_level.txt
swh_scrubber-4.0.0.dist-info/RECORD
