Metadata-Version: 2.4
Name: swh.scrubber
Version: 4.0.0
Summary: Software Heritage datastore scrubber
Author-email: Software Heritage developers <swh-devel@inria.fr>
Project-URL: Homepage, https://gitlab.softwareheritage.org/swh/devel/swh-scrubber
Project-URL: Bug Reports, https://gitlab.softwareheritage.org/swh/devel/swh-scrubber/-/issues
Project-URL: Funding, https://www.softwareheritage.org/donate
Project-URL: Documentation, https://docs.softwareheritage.org/devel/swh-scrubber/
Project-URL: Source, https://gitlab.softwareheritage.org/swh/devel/swh-scrubber.git
Classifier: Programming Language :: Python :: 3
Classifier: Intended Audience :: Developers
Classifier: License :: OSI Approved :: GNU General Public License v3 (GPLv3)
Classifier: Operating System :: OS Independent
Classifier: Development Status :: 3 - Alpha
Requires-Python: >=3.7
License-File: LICENSE
License-File: AUTHORS
Requires-Dist: dulwich
Requires-Dist: humanize
Requires-Dist: psycopg
Requires-Dist: tenacity
Requires-Dist: swh.core[http]>=4.0.0
Requires-Dist: swh.loader.git>=1.4.0
Requires-Dist: swh.model>=6.13.0
Requires-Dist: swh.storage>=3.0.0
Requires-Dist: swh.journal>=1.3.0
Requires-Dist: swh.objstorage>=2.9.2
Provides-Extra: testing
Requires-Dist: msgpack; extra == "testing"
Requires-Dist: msgpack-types; extra == "testing"
Requires-Dist: pytest>=8.1; extra == "testing"
Requires-Dist: pytest-mock; extra == "testing"
Requires-Dist: pyyaml; extra == "testing"
Requires-Dist: swh.core[testing]>=3.0.0; extra == "testing"
Requires-Dist: swh.graph; extra == "testing"
Requires-Dist: swh.storage[testing]; extra == "testing"
Dynamic: license-file
